.travis.yml
CHANGES.TXT
LICENSE.TXT
MANIFEST.in
README.rst
README.txt
USAGE.TXT
ez_setup.py
requirements.txt
setup.py
nested_dict/__init__.py
nested_dict/implementation.py
nested_dict.egg-info/PKG-INFO
nested_dict.egg-info/SOURCES.txt
nested_dict.egg-info/dependency_links.txt
nested_dict.egg-info/top_level.txt